data_rdb
