Metadata-Version: 2.1
Name: data-rdb
Version: 1.1.30
Summary: DataDBS for RethinkDB
Home-page: http://www.gitlab.com/dpineda/data_rdb
Author: David Pineda Osorio
Author-email: dpineda@csn.uchile.cl
License: MIT
Platform: UNKNOWN
